[  
   {  
      "category":"Bangla",
      "price":15.99,
      "instructions":"Hello",
      "photo":"http://3.bp.blogspot.com/-USH9DGW4k_c/UzG5xnKq-8I/AAAAAAAAAO4/9uusk5LadKU/s1600/%E0%A6%B8%E0%A6%AE%E0%A6%AF%E0%A6%BC-%E0%A6%9F%E0%A6%BF%E0%A6%AD%E0%A6%BF.jpg",
      "name":"Emon",
      "productId":1
   },
   {  
      "category":"Bangla",
      "price":33.99,
      "instructions":"Hello",
      "photo":"princess_flower.jpg",
      "name":"Masud",
      "productId":2
   },
   {  
      "category":"Bangla",
      "price":5.99,
      "instructions":"Hello",
      "photo":"mona_lavender.jpg",
      "name":"Shuhag",
      "productId":3
   },
   {  
      "category":"Bangla",
      "price":5.99,
      "instructions":"Hello",
      "photo":"mona_lavender.jpg",
      "name":"Tanbir",
      "productId":4
   }
]
